{"cameraMode":{"drawMode":0,"name":"Shaded","section":"Shading Mode"},"sceneLighting":true,"audioPlay":false,"sceneViewState":{"showFog":true,"showMaterialUpdate":false,"showSkybox":true,"showFlares":true,"showImageEffects":true,"showParticleSystems":true},"in2DMode":false,"pivot":{"x":172.94602966308595,"y":360.83392333984377,"z":-363.01849365234377},"rotation":{"x":-0.19269607961177827,"y":-0.11686356365680695,"z":0.023095248267054559,"w":-0.9740258455276489},"size":3.2660250663757326,"orthographic":false}